ghp_import2-1.0.1.dist-info/DESCRIPTION.rst
ghp_import2-1.0.1.dist-info/METADATA
ghp_import2-1.0.1.dist-info/entry_points.txt
ghp_import2-1.0.1.dist-info/top_level.txt
ghp_import2-1.0.1.dist-info/RECORD
ghp_import2-1.0.1.dist-info/WHEEL
ghp_import2-1.0.1.dist-info/metadata.json
ghp_import/cli.py
ghp_import/__main__.py
ghp_import/__init__.py
